pymontrace/__init__.py
pymontrace/__main__.py
pymontrace/_darwin.py
pymontrace/_tracebuffer.abi3.so
pymontrace/_tracebuffer.pyi
pymontrace/attacher.abi3.so
pymontrace/attacher.pyi
pymontrace/py.typed
pymontrace/tracebuffer.py
pymontrace/tracee.py
pymontrace/tracer.py
pymontrace-0.1.0.dev13.dist-info/METADATA
pymontrace-0.1.0.dev13.dist-info/WHEEL
pymontrace-0.1.0.dev13.dist-info/entry_points.txt
pymontrace-0.1.0.dev13.dist-info/top_level.txt
pymontrace-0.1.0.dev13.dist-info/RECORD
pymontrace-0.1.0.dev13.dist-info/licenses/LICENSE.txt
