Metadata-Version: 2.4
Name: pymontrace
Version: 0.1.0.dev13
Summary: dynamic python tracing
Author: Daniel Golding
License-Expression: MIT
Project-URL: Homepage, https://github.com/cakemanny/pymontrace
Project-URL: Documentation, https://cakemanny.com/pymontrace/
Project-URL: Repository, https://github.com/cakemanny/pymontrace.git
Keywords: tracing
Classifier: Development Status :: 3 - Alpha
Classifier: Environment :: Console
Classifier: Intended Audience :: Developers
Classifier: Operating System :: MacOS :: MacOS X
Classifier: Operating System :: POSIX :: Linux
Classifier: Topic :: Software Development :: Debuggers
Classifier: Programming Language :: Python :: 3
Classifier: Programming Language :: Python :: 3 :: Only
Classifier: Programming Language :: Python :: 3.9
Classifier: Programming Language :: Python :: 3.10
Classifier: Programming Language :: Python :: 3.11
Classifier: Programming Language :: Python :: 3.12
Classifier: Programming Language :: Python :: 3.13
Requires-Python: >=3.9
License-File: LICENSE.txt
Provides-Extra: test
Requires-Dist: pytest~=8.0; extra == "test"
Requires-Dist: flake8~=7.0; extra == "test"
Provides-Extra: dev
Requires-Dist: black~=25.0; extra == "dev"
Requires-Dist: isort~=6.0; extra == "dev"
Requires-Dist: pyright~=1.0; extra == "dev"
Dynamic: license-file
